README.md
setup.py
pycloaker/__init__.py
pycloaker/funcs.py
pycloaker/pycloaker.py
pycloaker.egg-info/PKG-INFO
pycloaker.egg-info/SOURCES.txt
pycloaker.egg-info/dependency_links.txt
pycloaker.egg-info/requires.txt
pycloaker.egg-info/top_level.txt