Metadata-Version: 2.1
Name: pycloaker
Version: 0.0.4
Summary: Cloaking Module For Python
Home-page: https://github.com/0xe2d0/pycloaker
Download-URL: https://github.com/0xe2d0/pyshield/tarball/master
Author: 0xe2d0
License: MIT
Keywords: claoker,python-cloaking,pycloaker,cloaker,cloaking,seo,python cloaking,flask cloaking
Classifier: Development Status :: 1 - Planning
Classifier: Intended Audience :: Developers
Classifier: Topic :: Software Development :: Build Tools
Classifier: License :: OSI Approved :: MIT License
Classifier: Programming Language :: Python :: 3.6
Classifier: Programming Language :: Python :: 3.7
Classifier: Programming Language :: Python :: 3.8
Classifier: Programming Language :: Python :: 3.9
